pulp_deb/__init__.py
pulp_deb/app/__init__.py
pulp_deb/app/constants.py
pulp_deb/app/modelresource.py
pulp_deb/app/settings.py
pulp_deb/app/urls.py
pulp_deb/app/management/__init__.py
pulp_deb/app/management/commands/__init__.py
pulp_deb/app/management/commands/check_dangling_content.py
pulp_deb/app/migrations/0001_initial.py
pulp_deb/app/migrations/0001_initial_squashed_0031_add_domains.py
pulp_deb/app/migrations/0002_auto_20190905_1000.py
pulp_deb/app/migrations/0003_rename_package_field.py
pulp_deb/app/migrations/0004_auto_20191014_1722.py
pulp_deb/app/migrations/0005_rename_release_file.py
pulp_deb/app/migrations/0006_debrepository.py
pulp_deb/app/migrations/0007_create_metadata_models.py
pulp_deb/app/migrations/0008_debremote_gpgkey.py
pulp_deb/app/migrations/0009_apt_release_signing_service.py
pulp_deb/app/migrations/0010_debpublication_signing_service.py
pulp_deb/app/migrations/0011_rename_models_to_apt.py
pulp_deb/app/migrations/0012_auto_20200803_1337.py
pulp_deb/app/migrations/0013_aptremote_ignore_missing_package_indices.py
pulp_deb/app/migrations/0014_swap_distribution_model.py
pulp_deb/app/migrations/0015_add_custom_fields_to_packages.py
pulp_deb/app/migrations/0016_switch_to_newer_jsonfield_model.py
pulp_deb/app/migrations/0017_allow_longer_string_lists.py
pulp_deb/app/migrations/0018_textfield_conversion.py
pulp_deb/app/migrations/0019_immutable_metadata_constraints.py
pulp_deb/app/migrations/0020_remove_fk_relations_in_packageindex_and_installerfileindex.py
pulp_deb/app/migrations/0021_remove_release_from_structure_types.py
pulp_deb/app/migrations/0022_alter_aptdistribution_distribution_ptr_and_more.py
pulp_deb/app/migrations/0023_add_default_signing_services.py
pulp_deb/app/migrations/0024_add_release_fields.py
pulp_deb/app/migrations/0025_merge_colliding_structure_content.py
pulp_deb/app/migrations/0026_aptrepository_publish_upstream_release_fields.py
pulp_deb/app/migrations/0027_alter_aptpublication_structured.py
pulp_deb-3.8.1.dist-info/licenses/LICENSE
pulp_deb-3.8.1.dist-info/METADATA
pulp_deb-3.8.1.dist-info/WHEEL
pulp_deb-3.8.1.dist-info/entry_points.txt
pulp_deb-3.8.1.dist-info/top_level.txt
pulp_deb-3.8.1.dist-info/RECORD
