Metadata-Version: 2.4
Name: pulp-deb
Version: 3.8.1
Summary: pulp-deb plugin for the Pulp Project
Author-email: Matthias Dellweg <dellweg@atix.de>
Project-URL: Homepage, https://pulpproject.org
Project-URL: Documentation, https://pulpproject.org/pulp_deb/
Project-URL: Repository, https://github.com/pulp/pulp_deb
Project-URL: Bug Tracker, https://github.com/pulp/pulp_deb/issues
Project-URL: Changelog, https://pulpproject.org/pulp_deb/changes/
Classifier: License :: OSI Approved :: GNU General Public License v2 or later (GPLv2+)
Classifier: Operating System :: POSIX :: Linux
Classifier: Development Status :: 5 - Production/Stable
Classifier: Framework :: Django
Classifier: Programming Language :: Python
Classifier: Programming Language :: Python :: 3
Classifier: Programming Language :: Python :: 3.11
Classifier: Programming Language :: Python :: 3.12
Classifier: Programming Language :: Python :: 3.13
Requires-Python: >=3.11
License-File: LICENSE
Requires-Dist: pulpcore<3.115,>=3.85.0
Requires-Dist: python-debian<0.2.0,>=0.1.44
Requires-Dist: python-gnupg<0.6,>=0.5
Requires-Dist: jsonschema<5.0,>=4.6
Dynamic: license-file
